binarytree/__init__.py
binarytree/exceptions.py
binarytree/version.py
binarytree-6.5.1.dist-info/LICENSE
binarytree-6.5.1.dist-info/METADATA
binarytree-6.5.1.dist-info/WHEEL
binarytree-6.5.1.dist-info/top_level.txt
binarytree-6.5.1.dist-info/RECORD
