Metadata-Version: 2.1
Name: binarytree
Version: 6.5.1
Summary: Python Library for Studying Binary Trees
Home-page: https://github.com/joowani/binarytree
Author: Joohwan Oh
Author-email: joohwan.oh@outlook.com
License: MIT
Keywords: tree,heap,bst,education
Platform: UNKNOWN
Classifier: Intended Audience :: Developers
Classifier: License :: OSI Approved :: MIT License
Classifier: Natural Language :: English
Classifier: Operating System :: MacOS
Classifier: Operating System :: Microsoft :: Windows
Classifier: Operating System :: Unix
Classifier: Programming Language :: Python :: 3
Classifier: Topic :: Documentation :: Sphinx
Classifier: Topic :: Education
Requires-Python: >=3.7
Provides-Extra: dev
License-File: LICENSE
